backtesterrb30/__init__.py
backtesterrb30/historical_data_feeds/Dockerfile
backtesterrb30/historical_data_feeds/__init__.py
backtesterrb30/historical_data_feeds/functions.py
backtesterrb30/historical_data_feeds/historical_data_feeds.py
backtesterrb30/historical_data_feeds/historical_downloader.py
backtesterrb30/historical_data_feeds/requirements.txt
backtesterrb30/historical_data_feeds/run.py
backtesterrb30/libs/__init__.py
backtesterrb30/libs/communication_broker/__init__.py
backtesterrb30/libs/communication_broker/asyncio_broker.py
backtesterrb30/libs/communication_broker/broker_base.py
backtesterrb30/libs/communication_broker/zmq.py
backtesterrb30/libs/communication_broker/zmq_broker.py
backtesterrb30/libs/data_sources/__init__.py
backtesterrb30/libs/data_sources/binance/__init__.py
backtesterrb30/libs/data_sources/binance/binance.py
backtesterrb30/libs/data_sources/binance/binance_instruments.txt
backtesterrb30/libs/data_sources/coingecko/__init__.py
backtesterrb30/libs/data_sources/coingecko/coingecko.py
backtesterrb30/libs/data_sources/data_source_base.py
backtesterrb30/libs/data_sources/data_sources_list.py
backtesterrb30/libs/data_sources/dukascopy/__init__.py
backtesterrb30/libs/data_sources/dukascopy/dukascopy.py
backtesterrb30/libs/data_sources/exante/__init__.py
backtesterrb30/libs/data_sources/exante/exante.py
backtesterrb30/libs/data_sources/rb30/__init__.py
backtesterrb30/libs/data_sources/rb30/rb30_disk.py
backtesterrb30/libs/data_sources/tradingview/__init__.py
backtesterrb30/libs/data_sources/tradingview/downloader.py
backtesterrb30/libs/data_sources/tradingview/tradingview.py
backtesterrb30/libs/data_sources/utils.py
backtesterrb30/libs/interfaces/__init__.py
backtesterrb30/libs/interfaces/historical_data_feeds/__init__.py
backtesterrb30/libs/interfaces/historical_data_feeds/instrument_file.py
backtesterrb30/libs/interfaces/python_backtester/__init__.py
backtesterrb30/libs/interfaces/python_backtester/close_all_trades.py
backtesterrb30-0.1.17.dist-info/LICENSE
backtesterrb30-0.1.17.dist-info/METADATA
backtesterrb30-0.1.17.dist-info/WHEEL
backtesterrb30-0.1.17.dist-info/entry_points.txt
backtesterrb30-0.1.17.dist-info/RECORD
