Metadata-Version: 2.3
Name: backtesterrb30
Version: 0.1.17
Summary: Backtesting and data loading engine
Home-page: https://github.com/threeal/python-starter
License: Unlicense
Keywords: backtesting,market,finance,trading
Author: pazerny kormoran
Requires-Python: >=3.10,<4.0
Classifier: Development Status :: 1 - Planning
Classifier: Intended Audience :: Developers
Classifier: License :: OSI Approved
Classifier: License :: OSI Approved :: The Unlicense (Unlicense)
Classifier: Operating System :: OS Independent
Classifier: Programming Language :: Python :: 3
Classifier: Programming Language :: Python :: 3.10
Classifier: Programming Language :: Python :: 3.11
Classifier: Programming Language :: Python :: 3.12
Classifier: Programming Language :: Python :: 3.13
Classifier: Programming Language :: Python :: 3 :: Only
Classifier: Topic :: Software Development :: Libraries :: Python Modules
Requires-Dist: appdirs (==1.4.4)
Requires-Dist: asyncio (==3.4.3)
Requires-Dist: backoff (==2.2.1)
Requires-Dist: deepdiff (==4.0.5)
Requires-Dist: inflection (==0.3.1)
Requires-Dist: jwt (==1.3.1)
Requires-Dist: keyboard (==0.13.5)
Requires-Dist: matplotlib (>=3.9.2,<4.0.0)
Requires-Dist: numpy (==2.1.2)
Requires-Dist: pandas (==2.2.3)
Requires-Dist: pycoingecko (==3.1.0)
Requires-Dist: pydantic (==1.10.2)
Requires-Dist: python-binance (==1.0.16)
Requires-Dist: python-dotenv (==0.21.0)
Requires-Dist: pyzmq (==26.2.0)
Requires-Dist: requests
Requires-Dist: websocket-client (>=0.57.0,<0.58.0)
Project-URL: Repository, https://github.com/threeal/python-starter
